orouboros.py
orouboros-0.1.13.dist-info/LICENSE
orouboros-0.1.13.dist-info/METADATA
orouboros-0.1.13.dist-info/WHEEL
orouboros-0.1.13.dist-info/entry_points.txt
orouboros-0.1.13.dist-info/top_level.txt
orouboros-0.1.13.dist-info/RECORD
