Metadata-Version: 2.1
Name: orouboros
Version: 0.1.13
Summary: UNKNOWN
Home-page: https://github.com/waynew/orouboros
Author: Wayne Werner
Author-email: waynejwerner@gmail.com
License: UNKNOWN
Platform: UNKNOWN
Classifier: Development Status :: 3 - Alpha
Classifier: Environment :: Console
Classifier: Programming Language :: Python :: 3.6
Classifier: Programming Language :: Python :: 3.7
Classifier: Topic :: Office/Business
Classifier: Topic :: Utilities
License-File: LICENSE
Requires-Dist: aiosmtpd
